telemeter_reporter/__init__.py
telemeter_reporter/reporter.py
telemeter_reporter/uhc.py
telemeter_reporter-0.1.3.1.data/scripts/telemeter-reporter
telemeter_reporter-0.1.3.1.dist-info/LICENSE
telemeter_reporter-0.1.3.1.dist-info/METADATA
telemeter_reporter-0.1.3.1.dist-info/WHEEL
telemeter_reporter-0.1.3.1.dist-info/top_level.txt
telemeter_reporter-0.1.3.1.dist-info/RECORD
