Metadata-Version: 2.1
Name: telemeter-reporter
Version: 0.1.3.1
Summary: A tool for generating compliance reports based on Telemeter data.
Home-page: https://github.com/abyrne55/telemeter-reporter
Author: Anthony Byrne
Author-email: abyrne@redhat.com
License: UNKNOWN
Platform: UNKNOWN
Classifier: Programming Language :: Python :: 3.7
Classifier: License :: OSI Approved :: Apache Software License
Classifier: Operating System :: OS Independent
Classifier: Natural Language :: English
Requires-Dist: PyYAML (>=5.1.1)
Requires-Dist: certifi (>=2019.6.16)
Requires-Dist: requests (>=2.22.0)
Requires-Dist: PyJWT[crypto] (>=1.7.1)
Requires-Dist: prometheus-api-client (>=0.0.2b4)
Requires-Dist: tabulate (>=0.8.3)
Requires-Dist: typing (>=3.7.4)
Requires-Dist: htmlmin (>=0.1.12)
Requires-Dist: dateparser (>=0.7.1)
